annual_stats/__init__.py
annual_stats-0.1.0.dist-info/LICENSE.md
annual_stats-0.1.0.dist-info/METADATA
annual_stats-0.1.0.dist-info/WHEEL
annual_stats-0.1.0.dist-info/RECORD
