Metadata-Version: 2.1
Name: annual-stats
Version: 0.1.0
Summary: Annual Statistics for a zettelkasten. The Archive
License: MIT
Author: Will Simpson
Author-email: will@kestrelcreek.com
Requires-Python: >=3.8,<4.0
Classifier: License :: OSI Approved :: MIT License
Classifier: Programming Language :: Python :: 3
Classifier: Programming Language :: Python :: 3.8
Classifier: Programming Language :: Python :: 3.9
Classifier: Programming Language :: Python :: 3.10
Classifier: Programming Language :: Python :: 3.11
Requires-Dist: tabulate (>=0.9.0,<0.10.0)
